{
  "id": "sandstone-signal-day",
  "name": "Sandstone Signal — Day",
  "appearance": "light",
  "description": "The light half of Sandstone Signal: white sandstone paper with the same gold focus.",
  "colors": {
    "bg": "#F8EDD6",
    "bgSecondary": "#F4E4C3",
    "bgTertiary": "#EAD4A5",
    "bgPanel": "#F7EAD0",
    "bgHover": "#E2C789",
    "border": "#CBAA6D",
    "borderSubtle": "#E3CFA4",
    "borderLight": "#786036",
    "text": "#443A27",
    "textPrimary": "#2C2214",
    "textSecondary": "#6B5A3C",
    "textMuted": "#958265"
  },
  "editor": {
    "background": "#F8EDD6",
    "surface": "#F7EAD0",
    "surfaceElevated": "#F5E8CB",
    "gutter": "#F7EAD0",
    "scrollbarTrack": "#F5E8CB",
    "scrollbarThumb": "#C7BCA8",
    "scrollbarThumbHover": "#A69780",
    "border": "#E3CFA4",
    "borderStrong": "#CBAA6D",
    "text": "#443A27",
    "textSoft": "#6B5A3C",
    "textMuted": "#958265",
    "caret": "#8A5714",
    "activeLine": "rgba(138, 87, 20, 0.11)",
    "activeLineGutter": "#8A5714",
    "selection": "rgba(138, 87, 20, 0.2)",
    "selectionInactive": "rgba(138, 87, 20, 0.12)",
    "selectionMatch": "rgba(138, 87, 20, 0.18)",
    "bracketMatch": "rgba(138, 87, 20, 0.22)",
    "searchMatch": "rgba(138, 87, 20, 0.28)",
    "tooltipBg": "#F8EDD6",
    "tooltipBgStrong": "#F7EAD0",
    "tooltipShadow": "inset 0 1px 0 rgba(255, 255, 255, 0.86), 0 18px 38px -24px rgba(44, 34, 20, 0.25), 0 28px 70px -42px rgba(44, 34, 20, 0.18)",
    "ghostText": "rgba(68, 58, 39, 0.34)",
    "highlight": "rgba(138, 87, 20, 0.1)",
    "comment": "#958265",
    "string": "#327A54",
    "number": "#8A5714",
    "keyword": "#B55551",
    "operator": "#6B5A3C",
    "type": "#167D78",
    "property": "#7B59A4",
    "function": "#8A5714",
    "variable": "#443A27",
    "constant": "#8A5714",
    "accent": "#8A5714"
  },
  "terminal": {
    "background": "#F8EDD6",
    "foreground": "#443A27",
    "cursor": "#8A5714",
    "cursorAccent": "#F8EDD6",
    "selectionBackground": "rgba(138, 87, 20, 0.2)",
    "black": "#2C2214",
    "red": "#B55551",
    "green": "#327A54",
    "yellow": "#8A5714",
    "blue": "#2D70AF",
    "magenta": "#7B59A4",
    "cyan": "#167D78",
    "white": "#443A27",
    "brightBlack": "#958265",
    "brightRed": "#A7504B",
    "brightGreen": "#31714E",
    "brightYellow": "#825314",
    "brightBlue": "#2D68A0",
    "brightMagenta": "#735496",
    "brightCyan": "#18746E",
    "brightWhite": "#2C2214"
  }
}
